tympeg/__init__.py
tympeg/concat.py
tympeg/converter.py
tympeg/mediaobject.py
tympeg/queue.py
tympeg/sandbox.py
tympeg/streamsaver.py
tympeg/timecode.py
tympeg/tools.py
tympeg/util.py
tympeg/scripts/__init__.py
tympeg/scripts/conversion_counter.py
tympeg/scripts/conversion_counter_UI.py
tympeg/scripts/convert_sub_dirs.py
tympeg/scripts/file_name_cleaner.py
tympeg/scripts/find_invalid_files.py
tympeg/scripts/pooled_converter.py
tympeg-0.2.9.dist-info/LICENSE
tympeg-0.2.9.dist-info/METADATA
tympeg-0.2.9.dist-info/WHEEL
tympeg-0.2.9.dist-info/top_level.txt
tympeg-0.2.9.dist-info/RECORD
