Metadata-Version: 2.1
Name: tympeg
Version: 0.2.9
Summary: Yet another scripting solution for ffmpeg operations: Converting, concatanating, saving HLS streams, meta-data analysis
Home-page: https://github.com/taishengy/tympeg
Author: TaiSheng Yeager
Author-email: taishengyeager@gmail.com
License: MIT
Keywords: ffmpeg video audio subtitle HLS stream
Platform: UNKNOWN
Requires-Dist: docutils (>=0.3)
